pytest_phoenix_interface/__init__.py
pytest_phoenix_interface-0.0.0.dist-info/METADATA
pytest_phoenix_interface-0.0.0.dist-info/WHEEL
pytest_phoenix_interface-0.0.0.dist-info/top_level.txt
pytest_phoenix_interface-0.0.0.dist-info/RECORD
